src/__init__.py
src/PyEncryption.py
py_encryption-0.1.1.dist-info/DESCRIPTION.rst
py_encryption-0.1.1.dist-info/METADATA
py_encryption-0.1.1.dist-info/metadata.json
py_encryption-0.1.1.dist-info/WHEEL
py_encryption-0.1.1.dist-info/top_level.txt
py_encryption-0.1.1.dist-info/RECORD
