Metadata-Version: 2.0
Name: py-encryption
Version: 0.1.1
Summary: Simple Encryption in Python.
Home-page: https://github.com/veridu/py-encryption
Author: Veridu Ltd
Author-email: contact@veridu.com
License: MIT
Keywords: security,encryption,AES,cipher,cryptography,symmetric key cryptography,crypto
Platform: UNKNOWN
Classifier: Development Status :: 3 - Alpha
Classifier: Intended Audience :: Developers
Classifier: Topic :: Software Development :: Build Tools
Classifier: License :: OSI Approved :: MIT License
Classifier: Programming Language :: Python :: 2
Classifier: Programming Language :: Python :: 2.6
Classifier: Programming Language :: Python :: 2.7
Classifier: Programming Language :: Python :: 3
Classifier: Programming Language :: Python :: 3.2
Classifier: Programming Language :: Python :: 3.3
Classifier: Programming Language :: Python :: 3.4
Classifier: Programming Language :: Python :: 3.5
